nurnotes/__init__.py
nurnotes/explain.py
nurnotes-0.1.0.dist-info/METADATA
nurnotes-0.1.0.dist-info/WHEEL
nurnotes-0.1.0.dist-info/top_level.txt
nurnotes-0.1.0.dist-info/RECORD
