Metadata-Version: 2.4
Name: nurnotes
Version: 0.1.0
Summary: Risale-i Nur cümlələrinin izahını verən sadə Python kitabxanası
Home-page: https://github.com/username/nurnotes
Author: Eldar Eliyev
Classifier: Programming Language :: Python :: 3
Classifier: License :: OSI Approved :: MIT License
Dynamic: author
Dynamic: classifier
Dynamic: home-page
Dynamic: summary
